shell_helper_auth/__init__.py
shell_helper_auth-0.2.1.dist-info/LICENSE
shell_helper_auth-0.2.1.dist-info/WHEEL
shell_helper_auth-0.2.1.dist-info/METADATA
shell_helper_auth-0.2.1.dist-info/RECORD
