Metadata-Version: 2.1
Name: shell-helper-auth
Version: 0.2.1
Summary: Requests authentication using shell helpers
Home-page: https://github.com/mportesdev/shell-helper-auth
License: MIT
Author: Michal Porteš
Author-email: michalportes1@gmail.com
Requires-Python: >=3.7,<4.0
Classifier: License :: OSI Approved :: MIT License
Classifier: Programming Language :: Python :: 3
Classifier: Programming Language :: Python :: 3.7
Classifier: Programming Language :: Python :: 3.8
Classifier: Programming Language :: Python :: 3.9
Classifier: Programming Language :: Python :: 3.10
Classifier: Programming Language :: Python :: 3.11
Requires-Dist: requests (>=2,<3)
